./.gitignore
./PKG-INFO
./README.md
./pyproject.toml
./mp_explore_source_bundestag/__init__.py
mp_explore_source_bundestag-0.1.1.dist-info/METADATA
mp_explore_source_bundestag-0.1.1.dist-info/WHEEL
mp_explore_source_bundestag-0.1.1.dist-info/RECORD
