Metadata-Version: 2.4
Name: mp_explore_source_bundestag
Version: 0.1.1
Summary: Obtain data of Bundestag MPs
Project-URL: Homepage, https://git.fsfe.org/mp-explore/mp-explore
Project-URL: Issues, https://git.fsfe.org/mp-explore/mp-explore/issues
Author-email: "Free Software Foundation Europe e.V." <mp-explore@fsfe.org>
Maintainer-email: Sofía Aritz <sofiaritz@fsfe.org>
License-Expression: AGPL-3.0-or-later
Classifier: Development Status :: 4 - Beta
Classifier: Intended Audience :: Developers
Classifier: License :: OSI Approved :: GNU Affero General Public License v3
Classifier: Programming Language :: Python :: 3.11
Classifier: Typing :: Typed
Requires-Python: >=3.11
Requires-Dist: mp-explore-core>=0.1.0
Requires-Dist: pandas>=2
Requires-Dist: playwright>=1.50
